gitsshgen/__init__.py
gitsshgen/gitsshgen.py
gitsshgen/helpers.py
gitsshgen/modules/__init__.py
gitsshgen/modules/bitbucket.py
gitsshgen/modules/gitea.py
gitsshgen/modules/github.py
gitsshgen/modules/gitlab.py
gitsshgen/modules/gogs.py
gitsshgen-1.2.3.dist-info/LICENSE
gitsshgen-1.2.3.dist-info/METADATA
gitsshgen-1.2.3.dist-info/WHEEL
gitsshgen-1.2.3.dist-info/entry_points.txt
gitsshgen-1.2.3.dist-info/top_level.txt
gitsshgen-1.2.3.dist-info/RECORD
