Metadata-Version: 2.1
Name: gitsshgen
Version: 1.2.3
Summary: Automatic generation of SSH keys for VCS
Home-page: https://github.com/dimon222/py-gitsshgen
Author: Dmitry Romanenko
Author-email: Dmitry@Romanenko.in
License: Apache License 2.0
Platform: UNKNOWN
Classifier: License :: OSI Approved :: Apache Software License
Classifier: Topic :: Software Development :: Version Control :: Git
Classifier: Topic :: Security :: Cryptography
Classifier: Environment :: Console
Classifier: Programming Language :: Python
Classifier: Programming Language :: Python :: 3
Classifier: Operating System :: OS Independent
Requires-Python: >=3.6
Requires-Dist: requests
Requires-Dist: asyncssh
